proc_mem_monitor/__init__.py
proc_mem_monitor/proc_mem_gui.py
proc_mem_monitor/proc_mem_handler.py
proc_mem_monitor/proc_mem_monitor.py
proc_mem_monitor/proc_mem_nogui.py
proc_mem_monitor/proc_mem_plot.py
proc_mem_monitor/resources/proc-mem-monitor-config.json
proc_mem_monitor/resources/proc-mem-monitor-icon.gif
proc_mem_monitor-0.0.3.dist-info/LICENSE
proc_mem_monitor-0.0.3.dist-info/METADATA
proc_mem_monitor-0.0.3.dist-info/WHEEL
proc_mem_monitor-0.0.3.dist-info/entry_points.txt
proc_mem_monitor-0.0.3.dist-info/top_level.txt
proc_mem_monitor-0.0.3.dist-info/RECORD
