Metadata-Version: 2.1
Name: proc-mem-monitor
Version: 0.0.3
Summary: Process Memory Monitor
Home-page: https://github.com/jimw567/proc-mem-monitor
Author: Jim Wu
Author-email: jimw567@gmail.com
License: UNKNOWN
Platform: UNKNOWN
Classifier: Programming Language :: Python :: 3
Classifier: License :: OSI Approved :: MIT License
Classifier: Operating System :: OS Independent
Requires-Dist: pandas
Requires-Dist: matplotlib
Requires-Dist: tksheet
